<?xml version="1.0" encoding="UTF-8" standalone="yes"?>
<document xmlns="http://www.abbyy.com/FineReader_xml/FineReader10-schema-v1.xml" version="1.0" producer="ABBYY FineReader Engine 12" languages="" xmlns:xsi="http://www.w3.org/2001/XMLSchema-instance" xsi:schemaLocation="http://www.abbyy.com/FineReader_xml/FineReader10-schema-v1.xml http://www.abbyy.com/FineReader_xml/FineReader10-schema-v1.xml">
<page width="1240" height="1755" resolution="150" originalCoords="1">
<block blockType="Text" blockName="" l="468" t="149" r="771" b="175"><region><rect l="468" t="149" r="771" b="175"/></region>
<text>
<par align="Center" lineSpacing="1260">
<line baseline="169" l="471" t="152" r="768" b="172"><formatting lang="EnglishUnitedStates">
<charParams l="471" t="152" r="487" b="168">O</charParams>
<charParams l="488" t="153" r="497" b="168">t</charParams>
<charParams l="499" t="152" r="510" b="168">h</charParams>
<charParams l="513" t="156" r="525" b="168">e</charParams>
<charParams l="528" t="156" r="536" b="167">r</charParams>
<charParams l="537" t="156" r="543" b="168"> </charParams>
<charParams l="544" t="156" r="556" b="168">o</charParams>
<charParams l="559" t="156" r="568" b="167">r</charParams>
<charParams l="569" t="156" r="581" b="172">g</charParams>
<charParams l="583" t="156" r="595" b="168">a</charParams>
<charParams l="598" t="156" r="610" b="167">n</charParams>
<charParams l="613" t="152" r="617" b="168">i</charParams>
<charParams l="619" t="156" r="630" b="168">c</charParams>
<charParams l="631" t="156" r="638" b="168"> </charParams>
<charParams l="639" t="156" r="649" b="168">s</charParams>
<charParams l="652" t="156" r="663" b="168">u</charParams>
<charParams l="667" t="152" r="679" b="168">b</charParams>
<charParams l="681" t="156" r="691" b="168">s</charParams>
<charParams l="692" t="153" r="701" b="168">t</charParams>
<charParams l="702" t="156" r="714" b="168">a</charParams>
<charParams l="717" t="156" r="728" b="168">n</charParams>
<charParams l="731" t="156" r="742" b="168">c</charParams>
<charParams l="743" t="156" r="755" b="168">e</charParams>
<charParams l="757" t="156" r="768" b="168">s</charParams></formatting></line></par>
</text>
</block>
<block blockType="Table" blockName="" l="203" t="195" r="1038" b="731"><region><rect l="424" t="195" r="1038" b="196"/><rect l="203" t="196" r="1038" b="728"/><rect l="233" t="728" r="1038" b="729"/><rect l="513" t="729" r="1038" b="730"/><rect l="860" t="730" r="1038" b="731"/></region>
<row>
<cell width="465" height="28">
<text>
<par lineSpacing="920"></par>
</text></cell>
<cell colSpan="3" width="370" height="28">
<text>
<par align="Center" lineSpacing="1150">
<line baseline="219" l="722" t="202" r="982" b="218"><formatting lang="EnglishUnitedStates">
<charParams l="722" t="202" r="735" b="218" suspicious="1">T</charParams>
<charParams l="737" t="205" r="748" b="218" suspicious="1">h</charParams>
<charParams l="751" t="206" r="762" b="218" suspicious="1">r</charParams>
<charParams l="764" t="206" r="773" b="218">e</charParams>
<charParams l="775" t="205" r="785" b="218" suspicious="1">s</charParams>
<charParams l="787" t="206" r="798" b="218">h</charParams>
<charParams l="801" t="205" r="813" b="218" suspicious="1">o</charParams>
<charParams l="815" t="206" r="824" b="218" suspicious="1">l</charParams>
<charParams l="826" t="206" r="837" b="218">d</charParams>
<charParams l="838" t="206" r="845" b="218"> </charParams>
<charParams l="846" t="206" r="854" b="218" suspicious="1">f</charParams>
<charParams l="856" t="206" r="868" b="218">o</charParams>
<charParams l="871" t="206" r="882" b="217" suspicious="1">r</charParams>
<charParams l="883" t="206" r="889" b="217"> </charParams>
<charParams l="890" t="206" r="901" b="217" suspicious="1">r</charParams>
<charParams l="903" t="205" r="911" b="217" suspicious="1">e</charParams>
<charParams l="914" t="205" r="922" b="217" suspicious="1">l</charParams>
<charParams l="924" t="205" r="933" b="217" suspicious="1">e</charParams>
<charParams l="935" t="205" r="947" b="217" suspicious="1">a</charParams>
<charParams l="948" t="205" r="958" b="218" suspicious="1">s</charParams>
<charParams l="960" t="205" r="969" b="217" suspicious="1">e</charParams>
<charParams l="971" t="205" r="982" b="218">s</charParams></formatting></line></par>
</text></cell></row>
<row>
<cell width="465" height="41">
<text>
<par lineSpacing="920"></par>
</text></cell>
<cell width="126" height="41">
<text>
<par align="Center" lineSpacing="960">
<line baseline="241" l="705" t="227" r="754" b="240"><formatting lang="EnglishUnitedStates">
<charParams l="705" t="228" r="712" b="240">t</charParams>
<charParams l="714" t="230" r="723" b="240">o</charParams>
<charParams l="724" t="230" r="729" b="240"> </charParams>
<charParams l="730" t="230" r="739" b="240">a</charParams>
<charParams l="742" t="227" r="745" b="240">i</charParams>
<charParams l="748" t="231" r="754" b="239">r</charParams></formatting></line>
<line baseline="260" l="693" t="247" r="767" b="263"><formatting lang="EnglishUnitedStates">
<charParams l="693" t="247" r="703" b="259">k</charParams>
<charParams l="704" t="250" r="714" b="263">g</charParams>
<charParams l="716" t="247" r="724" b="262">/</charParams>
<charParams l="727" t="250" r="737" b="263">y</charParams>
<charParams l="738" t="250" r="747" b="260">e</charParams>
<charParams l="749" t="250" r="758" b="260">a</charParams>
<charParams l="761" t="251" r="767" b="259">r</charParams></formatting></line></par>
</text></cell>
<cell width="112" height="41">
<text>
<par align="Center" lineSpacing="960">
<line baseline="240" l="810" t="228" r="888" b="240"><formatting lang="EnglishUnitedStates">
<charParams l="810" t="228" r="817" b="240">t</charParams>
<charParams l="818" t="230" r="828" b="240">o</charParams>
<charParams l="829" t="230" r="834" b="240"> </charParams>
<charParams l="835" t="231" r="850" b="240">w</charParams>
<charParams l="851" t="230" r="860" b="240">a</charParams>
<charParams l="862" t="228" r="869" b="240">t</charParams>
<charParams l="870" t="230" r="879" b="240">e</charParams>
<charParams l="882" t="230" r="888" b="239">r</charParams></formatting></line>
<line baseline="260" l="813" t="247" r="886" b="263"><formatting lang="EnglishUnitedStates">
<charParams l="813" t="247" r="822" b="260">k</charParams>
<charParams l="823" t="250" r="833" b="263">g</charParams>
<charParams l="836" t="247" r="844" b="262">/</charParams>
<charParams l="846" t="250" r="856" b="263">y</charParams>
<charParams l="857" t="250" r="867" b="260">e</charParams>
<charParams l="868" t="250" r="877" b="260">a</charParams>
<charParams l="880" t="250" r="886" b="259">r</charParams></formatting></line></par>
</text></cell>
<cell width="132" height="41">
<text>
<par align="Center" lineSpacing="912">
<line baseline="241" l="939" t="227" r="1002" b="240"><formatting lang="EnglishUnitedStates">
<charParams l="939" t="228" r="946" b="239">t</charParams>
<charParams l="947" t="230" r="957" b="240">o</charParams>
<charParams l="958" t="227" r="964" b="240"> </charParams>
<charParams l="965" t="227" r="967" b="239">l</charParams>
<charParams l="969" t="230" r="978" b="240">a</charParams>
<charParams l="981" t="230" r="990" b="239">n</charParams>
<charParams l="993" t="227" r="1002" b="240">d</charParams></formatting></line>
<line baseline="260" l="935" t="247" r="1008" b="262"><formatting lang="EnglishUnitedStates">
<charParams l="935" t="247" r="944" b="259">k</charParams>
<charParams l="945" t="250" r="955" b="262">g</charParams>
<charParams l="957" t="247" r="965" b="262">/</charParams>
<charParams l="968" t="250" r="978" b="262">y</charParams>
<charParams l="979" t="250" r="988" b="259">e</charParams>
<charParams l="990" t="250" r="999" b="259">a</charParams>
<charParams l="1002" t="250" r="1008" b="259">r</charParams></formatting></line></par>
</text></cell></row>
<row>
<cell width="465" height="22">
<text>
<par lineSpacing="920">
<line baseline="281" l="215" t="268" r="321" b="281"><formatting lang="EnglishUnitedStates">
<charParams l="215" t="269" r="227" b="281">A</charParams>
<charParams l="229" t="272" r="238" b="281">n</charParams>
<charParams l="240" t="269" r="246" b="281">t</charParams>
<charParams l="248" t="268" r="257" b="281">h</charParams>
<charParams l="260" t="272" r="266" b="281">r</charParams>
<charParams l="268" t="272" r="277" b="281">a</charParams>
<charParams l="279" t="272" r="287" b="281">c</charParams>
<charParams l="289" t="272" r="298" b="281">e</charParams>
<charParams l="300" t="272" r="309" b="281">n</charParams>
<charParams l="311" t="272" r="321" b="281">e</charParams></formatting></line></par>
</text></cell>
<cell width="126" height="22">
<text>
<par align="Center" lineSpacing="980">
<line baseline="282" l="720" t="268" r="740" b="281"><formatting lang="EnglishUnitedStates">
<charParams l="720" t="268" r="729" b="281">5</charParams>
<charParams l="731" t="268" r="740" b="281">0</charParams></formatting></line></par>
</text></cell>
<cell width="112" height="22">
<text>
<par align="Center" lineSpacing="980">
<line baseline="282" l="846" t="268" r="853" b="281"><formatting lang="EnglishUnitedStates">
<charParams l="846" t="268" r="853" b="281">1</charParams></formatting></line></par>
</text></cell>
<cell width="132" height="22">
<text>
<par align="Center" lineSpacing="980">
<line baseline="282" l="968" t="268" r="975" b="281"><formatting lang="EnglishUnitedStates">
<charParams l="968" t="268" r="975" b="281">1</charParams></formatting></line></par>
</text></cell></row>
<row>
<cell width="465" height="41">
<text>
<par lineSpacing="920">
<line baseline="313" l="216" t="301" r="293" b="313"><formatting lang="EnglishUnitedStates">
<charParams l="216" t="301" r="226" b="313">B</charParams>
<charParams l="228" t="304" r="237" b="313">e</charParams>
<charParams l="239" t="304" r="249" b="313">n</charParams>
<charParams l="251" t="304" r="259" b="313">z</charParams>
<charParams l="261" t="304" r="270" b="313">e</charParams>
<charParams l="272" t="304" r="281" b="313">n</charParams>
<charParams l="284" t="304" r="293" b="313">e</charParams></formatting></line></par>
</text></cell>
<cell width="126" height="41">
<text>
<par align="Center" lineSpacing="980">
<line baseline="314" l="708" t="300" r="753" b="313"><formatting lang="EnglishUnitedStates">
<charParams l="708" t="300" r="715" b="313">1</charParams>
<charParams l="716" t="300" r="722" b="313"> </charParams>
<charParams l="723" t="300" r="732" b="313">0</charParams>
<charParams l="734" t="300" r="743" b="313">0</charParams>
<charParams l="745" t="300" r="753" b="313">0</charParams></formatting></line></par>
</text></cell>
<cell width="112" height="41">
<text>
<par align="Center" lineSpacing="960">
<line baseline="304" l="818" t="290" r="881" b="306"><formatting lang="EnglishUnitedStates">
<charParams l="818" t="290" r="827" b="303">2</charParams>
<charParams l="829" t="290" r="837" b="303">0</charParams>
<charParams l="839" t="290" r="848" b="303">0</charParams>
<charParams l="849" t="290" r="855" b="306"> </charParams>
<charParams l="856" t="290" r="861" b="306">(</charParams>
<charParams l="863" t="293" r="871" b="303">a</charParams>
<charParams l="873" t="293" r="881" b="303">s</charParams></formatting></line>
<line baseline="324" l="825" t="310" r="873" b="326"><formatting lang="EnglishUnitedStates">
<charParams l="825" t="310" r="834" b="323">B</charParams>
<charParams l="835" t="310" r="845" b="322">T</charParams>
<charParams l="846" t="310" r="855" b="323">E</charParams>
<charParams l="856" t="310" r="866" b="323">X</charParams>
<charParams l="868" t="310" r="873" b="326">)</charParams></formatting></line></par>
</text></cell>
<cell width="132" height="41">
<text>
<par align="Center" lineSpacing="912">
<line baseline="304" l="940" t="290" r="1002" b="306"><formatting lang="EnglishUnitedStates">
<charParams l="940" t="290" r="948" b="302">2</charParams>
<charParams l="951" t="290" r="959" b="303">0</charParams>
<charParams l="961" t="290" r="970" b="303">0</charParams>
<charParams l="971" t="290" r="977" b="306"> </charParams>
<charParams l="978" t="290" r="983" b="306">(</charParams>
<charParams l="985" t="293" r="993" b="303">a</charParams>
<charParams l="995" t="293" r="1002" b="303">s</charParams></formatting></line>
<line baseline="323" l="947" t="309" r="995" b="326"><formatting lang="EnglishUnitedStates">
<charParams l="947" t="310" r="956" b="322">B</charParams>
<charParams l="957" t="310" r="967" b="322">T</charParams>
<charParams l="968" t="310" r="976" b="322">E</charParams>
<charParams l="978" t="310" r="988" b="322">X</charParams>
<charParams l="991" t="309" r="995" b="326">)</charParams></formatting></line></par>
</text></cell></row>
<row>
<cell width="465" height="20">
<text>
<par lineSpacing="920">
<line baseline="345" l="216" t="330" r="411" b="347"><formatting lang="EnglishUnitedStates">
<charParams l="216" t="332" r="226" b="343">B</charParams>
<charParams l="228" t="335" r="237" b="343">e</charParams>
<charParams l="239" t="335" r="249" b="343">n</charParams>
<charParams l="251" t="335" r="259" b="343">z</charParams>
<charParams l="261" t="334" r="270" b="343">o</charParams>
<charParams l="273" t="330" r="278" b="347">(</charParams>
<charParams l="281" t="334" r="291" b="347">g</charParams>
<charParams l="293" t="340" r="297" b="346">,</charParams>
<charParams l="299" t="330" r="309" b="343">h</charParams>
<charParams l="310" t="340" r="314" b="346">,</charParams>
<charParams l="317" t="330" r="320" b="343">i</charParams>
<charParams l="324" t="330" r="329" b="347">)</charParams>
<charParams l="332" t="334" r="341" b="347">p</charParams>
<charParams l="343" t="334" r="353" b="343">e</charParams>
<charParams l="355" t="334" r="361" b="343">r</charParams>
<charParams l="362" t="334" r="372" b="347">y</charParams>
<charParams l="374" t="331" r="377" b="343">l</charParams>
<charParams l="379" t="334" r="388" b="343">e</charParams>
<charParams l="391" t="334" r="400" b="343">n</charParams>
<charParams l="402" t="334" r="411" b="344">e</charParams></formatting></line></par>
</text></cell>
<cell width="126" height="20">
<text>
<par align="Justified" startIndent="2700" lineSpacing="1150">
<line baseline="341" l="726" t="337" r="733" b="339"><formatting lang="EnglishUnitedStates">
<charParams l="726" t="337" r="733" b="339">-</charParams></formatting></line></par>
</text></cell>
<cell width="112" height="20">
<text>
<par align="Center" lineSpacing="980">
<line baseline="345" l="846" t="331" r="853" b="344"><formatting lang="EnglishUnitedStates">
<charParams l="846" t="331" r="853" b="344">1</charParams></formatting></line></par>
</text></cell>
<cell width="132" height="20">
<text>
<par align="Center" lineSpacing="980">
<line baseline="342" l="968" t="336" r="974" b="339"><formatting lang="EnglishUnitedStates">
<charParams l="968" t="336" r="974" b="339">-</charParams></formatting></line></par>
</text></cell></row>
<row>
<cell width="465" height="23">
<text>
<par lineSpacing="920">
<line baseline="366" l="216" t="352" r="552" b="368"><formatting lang="EnglishUnitedStates">
<charParams l="216" t="353" r="227" b="365">D</charParams>
<charParams l="229" t="352" r="232" b="365">i</charParams>
<charParams l="235" t="358" r="241" b="361">-</charParams>
<charParams l="243" t="352" r="249" b="368">(</charParams>
<charParams l="252" t="353" r="262" b="365">2</charParams>
<charParams l="264" t="359" r="269" b="361">-</charParams>
<charParams l="271" t="356" r="281" b="365">e</charParams>
<charParams l="282" t="353" r="289" b="365">t</charParams>
<charParams l="291" t="353" r="300" b="365">h</charParams>
<charParams l="302" t="356" r="311" b="368">y</charParams>
<charParams l="313" t="353" r="316" b="365">l</charParams>
<charParams l="317" t="352" r="324" b="365"> </charParams>
<charParams l="325" t="352" r="334" b="365">h</charParams>
<charParams l="336" t="356" r="346" b="365">e</charParams>
<charParams l="347" t="356" r="356" b="365">x</charParams>
<charParams l="358" t="356" r="368" b="368">y</charParams>
<charParams l="370" t="353" r="373" b="365">l</charParams>
<charParams l="376" t="353" r="382" b="368">)</charParams>
<charParams l="383" t="353" r="389" b="368"> </charParams>
<charParams l="390" t="356" r="400" b="368">p</charParams>
<charParams l="402" t="353" r="411" b="365">h</charParams>
<charParams l="413" t="354" r="420" b="366">t</charParams>
<charParams l="422" t="353" r="431" b="366">h</charParams>
<charParams l="433" t="356" r="442" b="366">a</charParams>
<charParams l="444" t="353" r="447" b="366">l</charParams>
<charParams l="449" t="356" r="458" b="366">a</charParams>
<charParams l="460" t="354" r="467" b="366">t</charParams>
<charParams l="468" t="356" r="478" b="366">e</charParams>
<charParams l="479" t="353" r="485" b="368"> </charParams>
<charParams l="486" t="353" r="491" b="368">(</charParams>
<charParams l="495" t="354" r="506" b="365">D</charParams>
<charParams l="509" t="354" r="517" b="365">E</charParams>
<charParams l="520" t="353" r="531" b="365">H</charParams>
<charParams l="534" t="354" r="544" b="365">P</charParams>
<charParams l="547" t="353" r="552" b="368">)</charParams></formatting></line></par>
</text></cell>
<cell width="126" height="23">
<text>
<par align="Center" lineSpacing="980">
<line baseline="367" l="721" t="353" r="740" b="366"><formatting lang="EnglishUnitedStates">
<charParams l="721" t="354" r="728" b="366">1</charParams>
<charParams l="731" t="353" r="740" b="366">0</charParams></formatting></line></par>
</text></cell>
<cell width="112" height="23">
<text>
<par align="Center" lineSpacing="980">
<line baseline="367" l="846" t="353" r="853" b="366"><formatting lang="EnglishUnitedStates">
<charParams l="846" t="353" r="853" b="366">1</charParams></formatting></line></par>
</text></cell>
<cell width="132" height="23">
<text>
<par align="Center" lineSpacing="980">
<line baseline="367" l="968" t="353" r="975" b="365"><formatting lang="EnglishUnitedStates">
<charParams l="968" t="353" r="975" b="365">1</charParams></formatting></line></par>
</text></cell></row>
<row>
<cell width="465" height="41">
<text>
<par lineSpacing="920">
<line baseline="397" l="216" t="384" r="345" b="400"><formatting lang="EnglishUnitedStates">
<charParams l="216" t="384" r="225" b="396">E</charParams>
<charParams l="226" t="384" r="233" b="396">t</charParams>
<charParams l="235" t="384" r="244" b="396">h</charParams>
<charParams l="246" t="387" r="255" b="400">y</charParams>
<charParams l="257" t="384" r="260" b="396">l</charParams>
<charParams l="261" t="384" r="268" b="396"> </charParams>
<charParams l="269" t="384" r="278" b="396">b</charParams>
<charParams l="280" t="387" r="289" b="396">e</charParams>
<charParams l="291" t="387" r="300" b="396">n</charParams>
<charParams l="303" t="387" r="311" b="396">z</charParams>
<charParams l="313" t="387" r="322" b="396">e</charParams>
<charParams l="324" t="387" r="333" b="396">n</charParams>
<charParams l="336" t="387" r="345" b="396">e</charParams></formatting></line></par>
</text></cell>
<cell width="126" height="41">
<text>
<par startIndent="2700" lineSpacing="920">
<line baseline="398" l="727" t="390" r="733" b="392"><formatting lang="EnglishUnitedStates">
<charParams l="727" t="390" r="733" b="392">-</charParams></formatting></line></par>
</text></cell>
<cell width="112" height="41">
<text>
<par align="Center" lineSpacing="912">
<line baseline="388" l="818" t="374" r="881" b="390"><formatting lang="EnglishUnitedStates">
<charParams l="818" t="374" r="827" b="387">2</charParams>
<charParams l="829" t="374" r="837" b="387">0</charParams>
<charParams l="839" t="374" r="848" b="387">0</charParams>
<charParams l="849" t="374" r="855" b="390"> </charParams>
<charParams l="856" t="374" r="861" b="390">(</charParams>
<charParams l="863" t="377" r="871" b="387">a</charParams>
<charParams l="873" t="377" r="881" b="387">s</charParams></formatting></line>
<line baseline="407" l="825" t="393" r="873" b="410"><formatting lang="EnglishUnitedStates">
<charParams l="825" t="394" r="834" b="407">B</charParams>
<charParams l="835" t="394" r="845" b="406">T</charParams>
<charParams l="846" t="394" r="855" b="406">E</charParams>
<charParams l="856" t="394" r="866" b="406">X</charParams>
<charParams l="868" t="393" r="873" b="410">)</charParams></formatting></line></par>
</text></cell>
<cell width="132" height="41">
<text>
<par align="Center" lineSpacing="960">
<line baseline="387" l="940" t="374" r="1002" b="390"><formatting lang="EnglishUnitedStates">
<charParams l="940" t="374" r="948" b="387">2</charParams>
<charParams l="951" t="374" r="959" b="387">0</charParams>
<charParams l="961" t="374" r="970" b="387">0</charParams>
<charParams l="971" t="374" r="977" b="390"> </charParams>
<charParams l="978" t="374" r="982" b="390">(</charParams>
<charParams l="985" t="377" r="993" b="387">a</charParams>
<charParams l="995" t="377" r="1002" b="387">s</charParams></formatting></line>
<line baseline="407" l="947" t="394" r="995" b="410"><formatting lang="EnglishUnitedStates">
<charParams l="947" t="395" r="956" b="407">B</charParams>
<charParams l="957" t="395" r="967" b="407">T</charParams>
<charParams l="968" t="395" r="976" b="407">E</charParams>
<charParams l="978" t="395" r="988" b="407">X</charParams>
<charParams l="991" t="394" r="995" b="410">)</charParams></formatting></line></par>
</text></cell></row>
<row>
<cell width="465" height="21">
<text>
<par lineSpacing="920">
<line baseline="429" l="216" t="415" r="351" b="431"><formatting lang="EnglishUnitedStates">
<charParams l="216" t="415" r="225" b="427">E</charParams>
<charParams l="226" t="416" r="233" b="427">t</charParams>
<charParams l="235" t="415" r="244" b="427">h</charParams>
<charParams l="246" t="418" r="255" b="431">y</charParams>
<charParams l="257" t="415" r="260" b="427">l</charParams>
<charParams l="262" t="418" r="272" b="427">e</charParams>
<charParams l="274" t="418" r="283" b="427">n</charParams>
<charParams l="285" t="418" r="295" b="428">e</charParams>
<charParams l="296" t="418" r="301" b="428"> </charParams>
<charParams l="302" t="418" r="312" b="428">o</charParams>
<charParams l="313" t="418" r="323" b="427">x</charParams>
<charParams l="325" t="415" r="328" b="427">i</charParams>
<charParams l="330" t="415" r="340" b="427">d</charParams>
<charParams l="342" t="418" r="351" b="427">e</charParams></formatting></line></par>
</text></cell>
<cell width="126" height="21">
<text>
<par align="Center" lineSpacing="980">
<line baseline="429" l="708" t="415" r="753" b="428"><formatting lang="EnglishUnitedStates">
<charParams l="708" t="416" r="715" b="428">1</charParams>
<charParams l="716" t="415" r="722" b="428"> </charParams>
<charParams l="723" t="415" r="732" b="428">0</charParams>
<charParams l="734" t="415" r="742" b="428">0</charParams>
<charParams l="745" t="415" r="753" b="428">0</charParams></formatting></line></par>
</text></cell>
<cell width="112" height="21">
<text>
<par startIndent="2100" lineSpacing="980">
<line baseline="429" l="841" t="415" r="859" b="428"><formatting lang="EnglishUnitedStates">
<charParams l="841" t="415" r="847" b="428">1</charParams>
<charParams l="850" t="415" r="859" b="428">0</charParams></formatting></line></par>
</text></cell>
<cell width="132" height="21">
<text>
<par align="Center" lineSpacing="980">
<line baseline="428" l="963" t="415" r="981" b="428"><formatting lang="EnglishUnitedStates">
<charParams l="963" t="416" r="969" b="428">1</charParams>
<charParams l="972" t="415" r="981" b="428">0</charParams></formatting></line></par>
</text></cell></row>
<row>
<cell width="465" height="22">
<text>
<par lineSpacing="920">
<line baseline="451" l="216" t="437" r="338" b="450"><formatting lang="EnglishUnitedStates">
<charParams l="216" t="437" r="225" b="449">F</charParams>
<charParams l="226" t="437" r="229" b="449">l</charParams>
<charParams l="232" t="440" r="241" b="450">u</charParams>
<charParams l="243" t="440" r="253" b="450">o</charParams>
<charParams l="255" t="440" r="262" b="449">r</charParams>
<charParams l="263" t="440" r="272" b="450">a</charParams>
<charParams l="275" t="440" r="284" b="449">n</charParams>
<charParams l="286" t="438" r="293" b="450">t</charParams>
<charParams l="294" t="437" r="303" b="449">h</charParams>
<charParams l="306" t="440" r="315" b="450">e</charParams>
<charParams l="317" t="440" r="326" b="449">n</charParams>
<charParams l="329" t="440" r="338" b="450">e</charParams></formatting></line></par>
</text></cell>
<cell width="126" height="22">
<text>
<par align="Justified" startIndent="2700" lineSpacing="920">
<line baseline="448" l="726" t="443" r="733" b="445"><formatting lang="EnglishUnitedStates">
<charParams l="726" t="443" r="733" b="445">-</charParams></formatting></line></par>
</text></cell>
<cell width="112" height="22">
<text>
<par align="Center" lineSpacing="980">
<line baseline="451" l="846" t="437" r="853" b="450"><formatting lang="EnglishUnitedStates">
<charParams l="846" t="437" r="853" b="450">1</charParams></formatting></line></par>
</text></cell>
<cell width="132" height="22">
<text>
<par align="Center" lineSpacing="980">
<line baseline="448" l="968" t="443" r="974" b="445"><formatting lang="EnglishUnitedStates">
<charParams l="968" t="443" r="974" b="445">-</charParams></formatting></line></par>
</text></cell></row>
<row>
<cell width="465" height="21">
<text>
<par lineSpacing="920">
<line baseline="472" l="216" t="458" r="333" b="474"><formatting lang="EnglishUnitedStates">
<charParams l="216" t="458" r="227" b="470">N</charParams>
<charParams l="229" t="461" r="238" b="471">a</charParams>
<charParams l="241" t="461" r="250" b="474">p</charParams>
<charParams l="253" t="458" r="262" b="470">h</charParams>
<charParams l="263" t="459" r="270" b="471">t</charParams>
<charParams l="272" t="458" r="281" b="471">h</charParams>
<charParams l="283" t="461" r="292" b="471">a</charParams>
<charParams l="295" t="458" r="298" b="470">l</charParams>
<charParams l="300" t="461" r="310" b="471">e</charParams>
<charParams l="312" t="461" r="321" b="470">n</charParams>
<charParams l="323" t="461" r="333" b="471">e</charParams></formatting></line></par>
</text></cell>
<cell width="126" height="21">
<text>
<par align="Center" lineSpacing="980">
<line baseline="472" l="716" t="458" r="745" b="471"><formatting lang="EnglishUnitedStates">
<charParams l="716" t="458" r="723" b="471">1</charParams>
<charParams l="726" t="458" r="734" b="471">0</charParams>
<charParams l="736" t="458" r="745" b="471">0</charParams></formatting></line></par>
</text></cell>
<cell width="112" height="21">
<text>
<par startIndent="2100" lineSpacing="980">
<line baseline="472" l="841" t="458" r="859" b="471"><formatting lang="EnglishUnitedStates">
<charParams l="841" t="458" r="847" b="471">1</charParams>
<charParams l="850" t="458" r="859" b="471">0</charParams></formatting></line></par>
</text></cell>
<cell width="132" height="21">
<text>
<par align="Center" lineSpacing="980">
<line baseline="471" l="962" t="458" r="981" b="471"><formatting lang="EnglishUnitedStates">
<charParams l="962" t="459" r="969" b="471">1</charParams>
<charParams l="972" t="458" r="981" b="471">0</charParams></formatting></line></par>
</text></cell></row>
<row>
<cell width="465" height="42">
<text>
<par lineSpacing="1008">
<line baseline="493" l="216" t="479" r="610" b="495"><formatting lang="EnglishUnitedStates">
<charParams l="216" t="479" r="227" b="491">N</charParams>
<charParams l="229" t="482" r="239" b="492">o</charParams>
<charParams l="241" t="482" r="250" b="492">n</charParams>
<charParams l="252" t="482" r="262" b="495">y</charParams>
<charParams l="264" t="479" r="267" b="492">l</charParams>
<charParams l="269" t="482" r="279" b="495">p</charParams>
<charParams l="281" t="479" r="290" b="492">h</charParams>
<charParams l="293" t="482" r="302" b="492">e</charParams>
<charParams l="304" t="482" r="313" b="492">n</charParams>
<charParams l="315" t="482" r="325" b="492">o</charParams>
<charParams l="327" t="479" r="330" b="491">l</charParams>
<charParams l="331" t="479" r="337" b="492"> </charParams>
<charParams l="338" t="482" r="347" b="492">a</charParams>
<charParams l="350" t="482" r="359" b="491">n</charParams>
<charParams l="361" t="479" r="371" b="492">d</charParams>
<charParams l="372" t="479" r="378" b="492"> </charParams>
<charParams l="379" t="480" r="390" b="492">N</charParams>
<charParams l="393" t="482" r="402" b="492">o</charParams>
<charParams l="405" t="482" r="414" b="492">n</charParams>
<charParams l="416" t="483" r="425" b="495">y</charParams>
<charParams l="427" t="479" r="430" b="492">l</charParams>
<charParams l="433" t="483" r="443" b="495">p</charParams>
<charParams l="445" t="479" r="454" b="492">h</charParams>
<charParams l="456" t="482" r="466" b="492">e</charParams>
<charParams l="468" t="482" r="477" b="492">n</charParams>
<charParams l="479" t="482" r="489" b="492">o</charParams>
<charParams l="491" t="479" r="494" b="492">l</charParams>
<charParams l="495" t="479" r="501" b="492"> </charParams>
<charParams l="502" t="482" r="511" b="492">e</charParams>
<charParams l="512" t="480" r="519" b="492">t</charParams>
<charParams l="521" t="479" r="530" b="491">h</charParams>
<charParams l="532" t="482" r="542" b="492">o</charParams>
<charParams l="544" t="482" r="554" b="491">x</charParams>
<charParams l="555" t="482" r="564" b="495">y</charParams>
<charParams l="566" t="479" r="569" b="491">l</charParams>
<charParams l="572" t="482" r="581" b="492">a</charParams>
<charParams l="582" t="480" r="589" b="492">t</charParams>
<charParams l="590" t="482" r="600" b="492">e</charParams>
<charParams l="602" t="482" r="610" b="492">s</charParams></formatting></line>
<line baseline="514" l="216" t="500" r="316" b="516"><formatting lang="EnglishUnitedStates">
<charParams l="216" t="500" r="221" b="516">(</charParams>
<charParams l="225" t="501" r="236" b="513">N</charParams>
<charParams l="239" t="501" r="249" b="513">P</charParams>
<charParams l="251" t="500" r="259" b="515">/</charParams>
<charParams l="263" t="501" r="273" b="513">N</charParams>
<charParams l="277" t="501" r="287" b="513">P</charParams>
<charParams l="289" t="501" r="298" b="513">E</charParams>
<charParams l="300" t="503" r="308" b="513">s</charParams>
<charParams l="311" t="500" r="316" b="516">)</charParams></formatting></line></par>
</text></cell>
<cell width="126" height="42">
<text>
<par startIndent="2700" lineSpacing="920">
<line baseline="503" l="727" t="495" r="733" b="497"><formatting lang="EnglishUnitedStates">
<charParams l="727" t="495" r="733" b="497">-</charParams></formatting></line></par>
</text></cell>
<cell width="112" height="42">
<text>
<par align="Center" lineSpacing="980">
<line baseline="503" l="846" t="489" r="853" b="502"><formatting lang="EnglishUnitedStates">
<charParams l="846" t="489" r="853" b="502">1</charParams></formatting></line></par>
</text></cell>
<cell width="132" height="42">
<text>
<par align="Center" lineSpacing="980">
<line baseline="502" l="968" t="489" r="975" b="502"><formatting lang="EnglishUnitedStates">
<charParams l="968" t="489" r="975" b="502" suspicious="1">1</charParams></formatting></line></par>
</text></cell></row>
<row>
<cell width="465" height="21">
<text>
<par lineSpacing="920">
<line baseline="535" l="215" t="521" r="605" b="537"><formatting lang="EnglishUnitedStates">
<charParams l="215" t="522" r="227" b="534">O</charParams>
<charParams l="229" t="524" r="237" b="534">c</charParams>
<charParams l="239" t="522" r="246" b="534">t</charParams>
<charParams l="246" t="525" r="256" b="537">y</charParams>
<charParams l="258" t="521" r="261" b="534">l</charParams>
<charParams l="264" t="524" r="273" b="537">p</charParams>
<charParams l="275" t="521" r="285" b="534">h</charParams>
<charParams l="287" t="524" r="296" b="534">e</charParams>
<charParams l="298" t="524" r="308" b="534">n</charParams>
<charParams l="310" t="524" r="319" b="534">o</charParams>
<charParams l="322" t="521" r="325" b="534">l</charParams>
<charParams l="327" t="524" r="335" b="534">s</charParams>
<charParams l="336" t="524" r="341" b="534"> </charParams>
<charParams l="342" t="524" r="351" b="534">a</charParams>
<charParams l="354" t="524" r="363" b="534">n</charParams>
<charParams l="365" t="521" r="375" b="534">d</charParams>
<charParams l="376" t="521" r="382" b="534"> </charParams>
<charParams l="383" t="524" r="392" b="534">o</charParams>
<charParams l="394" t="524" r="403" b="534">c</charParams>
<charParams l="403" t="522" r="410" b="534">t</charParams>
<charParams l="411" t="525" r="421" b="537">y</charParams>
<charParams l="423" t="521" r="426" b="534">l</charParams>
<charParams l="429" t="525" r="438" b="537">p</charParams>
<charParams l="440" t="521" r="449" b="534">h</charParams>
<charParams l="452" t="524" r="461" b="534">e</charParams>
<charParams l="463" t="525" r="473" b="534">n</charParams>
<charParams l="475" t="524" r="484" b="534">o</charParams>
<charParams l="487" t="521" r="490" b="534">l</charParams>
<charParams l="491" t="521" r="496" b="534"> </charParams>
<charParams l="497" t="524" r="507" b="534">e</charParams>
<charParams l="508" t="522" r="515" b="534">t</charParams>
<charParams l="517" t="521" r="526" b="533">h</charParams>
<charParams l="528" t="524" r="538" b="534">o</charParams>
<charParams l="539" t="524" r="549" b="533">x</charParams>
<charParams l="550" t="524" r="560" b="537">y</charParams>
<charParams l="562" t="521" r="565" b="533">l</charParams>
<charParams l="567" t="524" r="576" b="534">a</charParams>
<charParams l="578" t="522" r="585" b="533">t</charParams>
<charParams l="586" t="524" r="595" b="534">e</charParams>
<charParams l="597" t="524" r="605" b="534">s</charParams></formatting></line></par>
</text></cell>
<cell width="126" height="21">
<text>
<par align="Justified" startIndent="2700" lineSpacing="920">
<line baseline="532" l="726" t="527" r="733" b="529"><formatting lang="EnglishUnitedStates">
<charParams l="726" t="527" r="733" b="529">-</charParams></formatting></line></par>
</text></cell>
<cell width="112" height="21">
<text>
<par align="Center" lineSpacing="980">
<line baseline="535" l="846" t="521" r="852" b="534"><formatting lang="EnglishUnitedStates">
<charParams l="846" t="521" r="852" b="534">1</charParams></formatting></line></par>
</text></cell>
<cell width="132" height="21">
<text>
<par align="Center" lineSpacing="980">
<line baseline="532" l="967" t="527" r="974" b="529"><formatting lang="EnglishUnitedStates">
<charParams l="967" t="527" r="974" b="529">-</charParams></formatting></line></par>
</text></cell></row>
<row>
<cell width="465" height="21">
<text>
<par lineSpacing="920">
<line baseline="556" l="215" t="542" r="542" b="558"><formatting lang="EnglishUnitedStates">
<charParams l="215" t="543" r="227" b="555">O</charParams>
<charParams l="230" t="546" r="236" b="555">r</charParams>
<charParams l="238" t="546" r="247" b="558">g</charParams>
<charParams l="249" t="546" r="258" b="555">a</charParams>
<charParams l="261" t="546" r="270" b="555">n</charParams>
<charParams l="272" t="546" r="282" b="555">o</charParams>
<charParams l="283" t="543" r="290" b="555">t</charParams>
<charParams l="292" t="542" r="295" b="555">i</charParams>
<charParams l="297" t="546" r="307" b="555">n</charParams>
<charParams l="308" t="545" r="314" b="555"> </charParams>
<charParams l="315" t="545" r="323" b="555">c</charParams>
<charParams l="324" t="545" r="334" b="555">o</charParams>
<charParams l="336" t="545" r="351" b="555">m</charParams>
<charParams l="354" t="545" r="363" b="558">p</charParams>
<charParams l="365" t="545" r="375" b="555">o</charParams>
<charParams l="377" t="546" r="386" b="555">u</charParams>
<charParams l="389" t="546" r="398" b="555">n</charParams>
<charParams l="400" t="542" r="409" b="555">d</charParams>
<charParams l="412" t="545" r="420" b="555">s</charParams>
<charParams l="421" t="542" r="427" b="558"> </charParams>
<charParams l="428" t="542" r="434" b="558">(</charParams>
<charParams l="436" t="546" r="445" b="555">a</charParams>
<charParams l="447" t="546" r="456" b="555">s</charParams>
<charParams l="457" t="543" r="462" b="555"> </charParams>
<charParams l="463" t="543" r="470" b="555">t</charParams>
<charParams l="471" t="545" r="481" b="555">o</charParams>
<charParams l="482" t="543" r="489" b="555">t</charParams>
<charParams l="490" t="545" r="499" b="555">a</charParams>
<charParams l="501" t="542" r="504" b="554">l</charParams>
<charParams l="505" t="542" r="511" b="555"> </charParams>
<charParams l="512" t="542" r="523" b="555">S</charParams>
<charParams l="525" t="545" r="534" b="554">n</charParams>
<charParams l="537" t="542" r="542" b="558">)</charParams></formatting></line></par>
</text></cell>
<cell width="126" height="21">
<text>
<par startIndent="2700" lineSpacing="920">
<line baseline="553" l="727" t="548" r="733" b="550"><formatting lang="EnglishUnitedStates">
<charParams l="727" t="548" r="733" b="550">-</charParams></formatting></line></par>
</text></cell>
<cell width="112" height="21">
<text>
<par startIndent="2100" lineSpacing="980">
<line baseline="555" l="840" t="541" r="859" b="555"><formatting lang="EnglishUnitedStates">
<charParams l="840" t="542" r="848" b="555">5</charParams>
<charParams l="850" t="542" r="859" b="555">0</charParams></formatting></line></par>
</text></cell>
<cell width="132" height="21">
<text>
<par align="Center" lineSpacing="980">
<line baseline="555" l="962" t="542" r="981" b="555"><formatting lang="EnglishUnitedStates">
<charParams l="962" t="542" r="970" b="555">5</charParams>
<charParams l="972" t="542" r="981" b="555">0</charParams></formatting></line></par>
</text></cell></row>
<row>
<cell width="465" height="21">
<text>
<par lineSpacing="920">
<line baseline="577" l="216" t="563" r="398" b="579"><formatting lang="EnglishUnitedStates">
<charParams l="216" t="564" r="226" b="576">P</charParams>
<charParams l="228" t="563" r="237" b="576">h</charParams>
<charParams l="239" t="567" r="249" b="576">e</charParams>
<charParams l="251" t="567" r="260" b="576">n</charParams>
<charParams l="262" t="567" r="272" b="576">o</charParams>
<charParams l="274" t="563" r="277" b="576">l</charParams>
<charParams l="279" t="567" r="288" b="576">s</charParams>
<charParams l="289" t="563" r="295" b="579"> </charParams>
<charParams l="296" t="563" r="301" b="579">(</charParams>
<charParams l="304" t="567" r="313" b="576">a</charParams>
<charParams l="315" t="566" r="324" b="576">s</charParams>
<charParams l="325" t="564" r="329" b="576"> </charParams>
<charParams l="330" t="564" r="337" b="576">t</charParams>
<charParams l="338" t="566" r="348" b="576">o</charParams>
<charParams l="349" t="564" r="356" b="576">t</charParams>
<charParams l="357" t="566" r="366" b="576">a</charParams>
<charParams l="369" t="563" r="372" b="576">l</charParams>
<charParams l="373" t="563" r="379" b="576"> </charParams>
<charParams l="380" t="563" r="390" b="576">C</charParams>
<charParams l="393" t="563" r="398" b="579">)</charParams></formatting></line></par>
</text></cell>
<cell width="126" height="21">
<text>
<par startIndent="2700" lineSpacing="920">
<line baseline="574" l="727" t="569" r="733" b="571"><formatting lang="EnglishUnitedStates">
<charParams l="727" t="569" r="733" b="571">-</charParams></formatting></line></par>
</text></cell>
<cell width="112" height="21">
<text>
<par startIndent="2100" lineSpacing="920">
<line baseline="576" l="840" t="563" r="859" b="576"><formatting lang="EnglishUnitedStates">
<charParams l="840" t="563" r="848" b="576">2</charParams>
<charParams l="850" t="563" r="859" b="576">0</charParams></formatting></line></par>
</text></cell>
<cell width="132" height="21">
<text>
<par align="Center" lineSpacing="980">
<line baseline="576" l="962" t="563" r="981" b="576"><formatting lang="EnglishUnitedStates">
<charParams l="962" t="563" r="970" b="576">2</charParams>
<charParams l="972" t="563" r="981" b="576">0</charParams></formatting></line></par>
</text></cell></row>
<row>
<cell width="465" height="22">
<text>
<par lineSpacing="920">
<line baseline="599" l="216" t="585" r="601" b="601"><formatting lang="EnglishUnitedStates">
<charParams l="216" t="586" r="226" b="598">P</charParams>
<charParams l="227" t="589" r="237" b="598">o</charParams>
<charParams l="239" t="585" r="242" b="598">l</charParams>
<charParams l="244" t="589" r="254" b="601">y</charParams>
<charParams l="255" t="589" r="264" b="598">c</charParams>
<charParams l="265" t="589" r="274" b="601">y</charParams>
<charParams l="276" t="589" r="284" b="598">c</charParams>
<charParams l="286" t="585" r="289" b="598">l</charParams>
<charParams l="292" t="585" r="295" b="598">i</charParams>
<charParams l="297" t="589" r="306" b="598">c</charParams>
<charParams l="307" t="586" r="311" b="598"> </charParams>
<charParams l="312" t="586" r="324" b="598">A</charParams>
<charParams l="326" t="589" r="333" b="598">r</charParams>
<charParams l="334" t="588" r="344" b="598">o</charParams>
<charParams l="346" t="589" r="361" b="598">m</charParams>
<charParams l="363" t="588" r="372" b="598">a</charParams>
<charParams l="374" t="586" r="381" b="598">t</charParams>
<charParams l="382" t="585" r="385" b="598">i</charParams>
<charParams l="387" t="588" r="396" b="598">c</charParams>
<charParams l="397" t="585" r="402" b="598"> </charParams>
<charParams l="403" t="585" r="413" b="598">h</charParams>
<charParams l="415" t="589" r="424" b="601">y</charParams>
<charParams l="426" t="585" r="435" b="598">d</charParams>
<charParams l="438" t="589" r="444" b="598">r</charParams>
<charParams l="446" t="588" r="455" b="598">o</charParams>
<charParams l="457" t="588" r="465" b="598">c</charParams>
<charParams l="467" t="588" r="476" b="598">a</charParams>
<charParams l="478" t="589" r="485" b="598">r</charParams>
<charParams l="487" t="585" r="496" b="598">b</charParams>
<charParams l="498" t="588" r="508" b="598">o</charParams>
<charParams l="510" t="588" r="519" b="597">n</charParams>
<charParams l="521" t="588" r="530" b="598">s</charParams>
<charParams l="531" t="585" r="537" b="601"> </charParams>
<charParams l="538" t="585" r="543" b="601">(</charParams>
<charParams l="546" t="585" r="556" b="597">P</charParams>
<charParams l="557" t="585" r="570" b="597">A</charParams>
<charParams l="572" t="585" r="582" b="597">H</charParams>
<charParams l="585" t="588" r="593" b="598">s</charParams>
<charParams l="596" t="585" r="601" b="601">)</charParams></formatting></line></par>
</text></cell>
<cell width="126" height="22">
<text>
<par startIndent="2400" lineSpacing="980">
<line baseline="599" l="720" t="585" r="739" b="598"><formatting lang="EnglishUnitedStates">
<charParams l="720" t="585" r="729" b="598">5</charParams>
<charParams l="731" t="585" r="739" b="598">0</charParams></formatting></line></par>
</text></cell>
<cell width="112" height="22">
<text>
<par align="Center" lineSpacing="980">
<line baseline="598" l="845" t="585" r="853" b="598"><formatting lang="EnglishUnitedStates">
<charParams l="845" t="585" r="853" b="598">5</charParams></formatting></line></par>
</text></cell>
<cell width="132" height="22">
<text>
<par align="Center" lineSpacing="980">
<line baseline="598" l="967" t="585" r="975" b="598"><formatting lang="EnglishUnitedStates">
<charParams l="967" t="585" r="975" b="598">5</charParams></formatting></line></par>
</text></cell></row>
<row>
<cell width="465" height="41">
<text>
<par lineSpacing="920">
<line baseline="630" l="215" t="615" r="288" b="628"><formatting lang="EnglishUnitedStates">
<charParams l="215" t="616" r="225" b="628">T</charParams>
<charParams l="226" t="619" r="236" b="628">o</charParams>
<charParams l="238" t="615" r="241" b="628">l</charParams>
<charParams l="244" t="619" r="253" b="628">u</charParams>
<charParams l="255" t="619" r="265" b="628">e</charParams>
<charParams l="267" t="619" r="276" b="628">n</charParams>
<charParams l="278" t="619" r="288" b="628">e</charParams></formatting></line></par>
</text></cell>
<cell width="126" height="41">
<text>
<par startIndent="2700" lineSpacing="920">
<line baseline="630" l="727" t="622" r="733" b="624"><formatting lang="EnglishUnitedStates">
<charParams l="727" t="622" r="733" b="624">-</charParams></formatting></line></par>
</text></cell>
<cell width="112" height="41">
<text>
<par align="Center" lineSpacing="960">
<line baseline="619" l="818" t="606" r="881" b="622"><formatting lang="EnglishUnitedStates">
<charParams l="818" t="606" r="827" b="619">2</charParams>
<charParams l="829" t="606" r="837" b="619">0</charParams>
<charParams l="839" t="606" r="848" b="619">0</charParams>
<charParams l="849" t="606" r="855" b="622"> </charParams>
<charParams l="856" t="606" r="861" b="622">(</charParams>
<charParams l="863" t="609" r="871" b="619">a</charParams>
<charParams l="873" t="609" r="881" b="619">s</charParams></formatting></line>
<line baseline="639" l="825" t="626" r="873" b="642"><formatting lang="EnglishUnitedStates">
<charParams l="825" t="627" r="834" b="639">B</charParams>
<charParams l="835" t="626" r="845" b="639">T</charParams>
<charParams l="846" t="626" r="855" b="639">E</charParams>
<charParams l="856" t="626" r="866" b="639">X</charParams>
<charParams l="869" t="626" r="873" b="642">)</charParams></formatting></line></par>
</text></cell>
<cell width="132" height="41">
<text>
<par align="Center" lineSpacing="960">
<line baseline="619" l="940" t="605" r="1002" b="622"><formatting lang="EnglishUnitedStates">
<charParams l="940" t="606" r="948" b="618">2</charParams>
<charParams l="951" t="606" r="959" b="619">0</charParams>
<charParams l="961" t="606" r="970" b="619">0</charParams>
<charParams l="971" t="605" r="977" b="621"> </charParams>
<charParams l="978" t="605" r="983" b="621">(</charParams>
<charParams l="985" t="609" r="993" b="619">a</charParams>
<charParams l="995" t="608" r="1002" b="619">s</charParams></formatting></line>
<line baseline="638" l="947" t="625" r="995" b="642"><formatting lang="EnglishUnitedStates">
<charParams l="947" t="626" r="956" b="638">B</charParams>
<charParams l="957" t="626" r="967" b="638">T</charParams>
<charParams l="968" t="626" r="976" b="638">E</charParams>
<charParams l="978" t="626" r="988" b="639">X</charParams>
<charParams l="991" t="626" r="995" b="642">)</charParams></formatting></line></par>
</text></cell></row>
<row>
<cell width="465" height="42">
<text>
<par lineSpacing="1008">
<line baseline="662" l="215" t="647" r="601" b="665"><formatting lang="EnglishUnitedStates">
<charParams l="215" t="648" r="225" b="660">T</charParams>
<charParams l="226" t="651" r="236" b="660">o</charParams>
<charParams l="237" t="648" r="244" b="660">t</charParams>
<charParams l="246" t="651" r="255" b="660">a</charParams>
<charParams l="257" t="647" r="260" b="660">l</charParams>
<charParams l="261" t="647" r="267" b="660"> </charParams>
<charParams l="268" t="648" r="280" b="660">O</charParams>
<charParams l="283" t="651" r="289" b="660">r</charParams>
<charParams l="290" t="651" r="300" b="664">g</charParams>
<charParams l="302" t="651" r="311" b="660">a</charParams>
<charParams l="314" t="651" r="323" b="660">n</charParams>
<charParams l="326" t="647" r="329" b="660">i</charParams>
<charParams l="331" t="652" r="339" b="661">c</charParams>
<charParams l="340" t="649" r="345" b="661"> </charParams>
<charParams l="346" t="649" r="357" b="661">C</charParams>
<charParams l="358" t="652" r="367" b="661">a</charParams>
<charParams l="370" t="652" r="377" b="661">r</charParams>
<charParams l="378" t="648" r="388" b="661">b</charParams>
<charParams l="390" t="652" r="399" b="661">o</charParams>
<charParams l="401" t="652" r="411" b="661">n</charParams>
<charParams l="412" t="648" r="419" b="664"> </charParams>
<charParams l="420" t="648" r="425" b="664">(</charParams>
<charParams l="427" t="649" r="438" b="661">T</charParams>
<charParams l="439" t="649" r="451" b="661">O</charParams>
<charParams l="453" t="649" r="464" b="661">C</charParams>
<charParams l="466" t="648" r="472" b="664">)</charParams>
<charParams l="473" t="648" r="480" b="664"> </charParams>
<charParams l="481" t="648" r="486" b="664">(</charParams>
<charParams l="489" t="651" r="498" b="661">a</charParams>
<charParams l="500" t="651" r="508" b="661">s</charParams>
<charParams l="509" t="649" r="514" b="661"> </charParams>
<charParams l="515" t="649" r="522" b="660">t</charParams>
<charParams l="523" t="651" r="533" b="661">o</charParams>
<charParams l="534" t="649" r="541" b="660">t</charParams>
<charParams l="542" t="651" r="551" b="660">a</charParams>
<charParams l="554" t="648" r="557" b="660">l</charParams>
<charParams l="558" t="648" r="564" b="660"> </charParams>
<charParams l="565" t="648" r="575" b="660">C</charParams>
<charParams l="576" t="648" r="582" b="661"> </charParams>
<charParams l="583" t="651" r="592" b="661">o</charParams>
<charParams l="594" t="651" r="601" b="660">r</charParams></formatting></line>
<line baseline="682" l="215" t="668" r="285" b="684"><formatting lang="EnglishUnitedStates">
<charParams l="215" t="668" r="225" b="680">C</charParams>
<charParams l="227" t="668" r="239" b="680">O</charParams>
<charParams l="242" t="668" r="253" b="680">D</charParams>
<charParams l="256" t="668" r="264" b="683">/</charParams>
<charParams l="267" t="668" r="276" b="680">3</charParams>
<charParams l="280" t="668" r="285" b="684">)</charParams></formatting></line></par>
</text></cell>
<cell width="126" height="42">
<text>
<par startIndent="2700" lineSpacing="920">
<line baseline="672" l="727" t="664" r="733" b="666"><formatting lang="EnglishUnitedStates">
<charParams l="727" t="664" r="733" b="666">-</charParams></formatting></line></par>
</text></cell>
<cell width="112" height="42">
<text>
<par align="Center" lineSpacing="980">
<line baseline="671" l="821" t="658" r="878" b="671"><formatting lang="EnglishUnitedStates">
<charParams l="821" t="658" r="829" b="671">5</charParams>
<charParams l="831" t="658" r="840" b="671">0</charParams>
<charParams l="841" t="658" r="847" b="671"> </charParams>
<charParams l="848" t="658" r="856" b="671">0</charParams>
<charParams l="858" t="658" r="867" b="671">0</charParams>
<charParams l="869" t="658" r="878" b="671">0</charParams></formatting></line></par>
</text></cell>
<cell width="132" height="42">
<text>
<par align="Center" lineSpacing="980">
<line baseline="670" l="968" t="664" r="974" b="667"><formatting lang="EnglishUnitedStates">
<charParams l="968" t="664" r="974" b="667">-</charParams></formatting></line></par>
</text></cell></row>
<row>
<cell width="465" height="44">
<text>
<par lineSpacing="920">
<line baseline="714" l="215" t="699" r="287" b="715"><formatting lang="EnglishUnitedStates">
<charParams l="215" t="699" r="226" b="712">X</charParams>
<charParams l="228" t="702" r="237" b="715">y</charParams>
<charParams l="239" t="699" r="242" b="711">l</charParams>
<charParams l="244" t="702" r="254" b="712">e</charParams>
<charParams l="256" t="702" r="265" b="711">n</charParams>
<charParams l="267" t="702" r="277" b="712">e</charParams>
<charParams l="278" t="702" r="287" b="712">s</charParams></formatting></line></par>
</text></cell>
<cell width="126" height="44">
<text>
<par startIndent="2700" lineSpacing="920">
<line baseline="713" l="727" t="705" r="732" b="707"><formatting lang="EnglishUnitedStates">
<charParams l="727" t="705" r="732" b="707">-</charParams></formatting></line></par>
</text></cell>
<cell width="112" height="44">
<text>
<par align="Center" lineSpacing="960">
<line baseline="702" l="818" t="689" r="881" b="705"><formatting lang="EnglishUnitedStates">
<charParams l="818" t="689" r="827" b="702">2</charParams>
<charParams l="828" t="689" r="837" b="702">0</charParams>
<charParams l="839" t="689" r="848" b="702">0</charParams>
<charParams l="849" t="689" r="855" b="705"> </charParams>
<charParams l="856" t="689" r="861" b="705">(</charParams>
<charParams l="863" t="692" r="871" b="702">a</charParams>
<charParams l="873" t="692" r="881" b="702">s</charParams></formatting></line>
<line baseline="722" l="825" t="709" r="873" b="725"><formatting lang="EnglishUnitedStates">
<charParams l="825" t="709" r="834" b="722">B</charParams>
<charParams l="835" t="709" r="845" b="722">T</charParams>
<charParams l="846" t="709" r="855" b="722">E</charParams>
<charParams l="856" t="709" r="866" b="722">X</charParams>
<charParams l="868" t="709" r="873" b="725">)</charParams></formatting></line></par>
</text></cell>
<cell width="132" height="44">
<text>
<par align="Center" lineSpacing="960">
<line baseline="701" l="940" t="688" r="1002" b="705"><formatting lang="EnglishUnitedStates">
<charParams l="940" t="689" r="948" b="702">2</charParams>
<charParams l="951" t="689" r="959" b="702">0</charParams>
<charParams l="961" t="689" r="970" b="702">0</charParams>
<charParams l="971" t="689" r="977" b="705"> </charParams>
<charParams l="978" t="689" r="982" b="705">(</charParams>
<charParams l="985" t="692" r="993" b="702">a</charParams>
<charParams l="995" t="692" r="1002" b="702">s</charParams></formatting></line>
<line baseline="721" l="947" t="709" r="995" b="725"><formatting lang="EnglishUnitedStates">
<charParams l="947" t="710" r="956" b="722">B</charParams>
<charParams l="957" t="709" r="967" b="722">T</charParams>
<charParams l="968" t="709" r="977" b="722">E</charParams>
<charParams l="978" t="709" r="988" b="722">X</charParams>
<charParams l="991" t="709" r="995" b="725">)</charParams></formatting></line></par>
</text></cell></row>
</block>
<block blockType="Text" blockName="" l="493" t="769" r="748" b="795"><region><rect l="493" t="769" r="689" b="770"/><rect l="493" t="770" r="748" b="795"/></region>
<text>
<par align="Center" lineSpacing="1260">
<line baseline="789" l="495" t="771" r="745" b="791"><formatting lang="EnglishUnitedStates">
<charParams l="495" t="772" r="504" b="788">I</charParams>
<charParams l="507" t="776" r="518" b="787">n</charParams>
<charParams l="521" t="776" r="534" b="788">o</charParams>
<charParams l="536" t="776" r="544" b="787">r</charParams>
<charParams l="546" t="776" r="558" b="791">g</charParams>
<charParams l="560" t="776" r="572" b="787">a</charParams>
<charParams l="575" t="776" r="587" b="787">n</charParams>
<charParams l="590" t="771" r="594" b="787">i</charParams>
<charParams l="596" t="776" r="607" b="788">c</charParams>
<charParams l="608" t="776" r="615" b="788"> </charParams>
<charParams l="616" t="776" r="626" b="788">s</charParams>
<charParams l="629" t="776" r="640" b="788">u</charParams>
<charParams l="644" t="772" r="655" b="788">b</charParams>
<charParams l="658" t="776" r="668" b="788">s</charParams>
<charParams l="669" t="773" r="678" b="788">t</charParams>
<charParams l="679" t="776" r="691" b="788">a</charParams>
<charParams l="694" t="776" r="706" b="787">n</charParams>
<charParams l="708" t="776" r="719" b="788">c</charParams>
<charParams l="720" t="776" r="732" b="787">e</charParams>
<charParams l="734" t="776" r="745" b="787">s</charParams></formatting></line></par>
</text>
</block>
<block blockType="Table" blockName="" l="209" t="813" r="1032" b="1041"><region><rect l="209" t="813" r="327" b="814"/><rect l="209" t="814" r="689" b="815"/><rect l="209" t="815" r="841" b="816"/><rect l="209" t="816" r="969" b="817"/><rect l="209" t="817" r="1032" b="1035"/><rect l="257" t="1035" r="1032" b="1036"/><rect l="379" t="1036" r="1032" b="1037"/><rect l="513" t="1037" r="1032" b="1038"/><rect l="793" t="1038" r="1032" b="1039"/><rect l="886" t="1039" r="1032" b="1040"/><rect l="993" t="1040" r="1032" b="1041"/></region>
<row>
<cell width="463" height="29">
<text>
<par lineSpacing="920"></par>
</text></cell>
<cell colSpan="3" width="360" height="29">
<text>
<par startIndent="2200" lineSpacing="1150">
<line baseline="837" l="721" t="822" r="981" b="839"><formatting lang="EnglishUnitedStates">
<charParams l="721" t="822" r="734" b="837" suspicious="1">T</charParams>
<charParams l="736" t="825" r="747" b="837">h</charParams>
<charParams l="750" t="825" r="761" b="838">r</charParams>
<charParams l="763" t="826" r="772" b="838" suspicious="1">e</charParams>
<charParams l="774" t="826" r="784" b="838">s</charParams>
<charParams l="787" t="826" r="797" b="838">h</charParams>
<charParams l="800" t="825" r="812" b="838" suspicious="1">o</charParams>
<charParams l="815" t="826" r="823" b="838">l</charParams>
<charParams l="825" t="826" r="837" b="837">d</charParams>
<charParams l="838" t="825" r="844" b="837"> </charParams>
<charParams l="845" t="825" r="854" b="837">f</charParams>
<charParams l="855" t="825" r="868" b="837">o</charParams>
<charParams l="870" t="825" r="881" b="837">r</charParams>
<charParams l="882" t="825" r="888" b="838"> </charParams>
<charParams l="889" t="826" r="899" b="838">r</charParams>
<charParams l="902" t="826" r="910" b="838">e</charParams>
<charParams l="913" t="826" r="922" b="838">l</charParams>
<charParams l="923" t="826" r="932" b="838">e</charParams>
<charParams l="934" t="826" r="946" b="838">a</charParams>
<charParams l="947" t="825" r="958" b="838">s</charParams>
<charParams l="960" t="825" r="968" b="837">e</charParams>
<charParams l="971" t="825" r="981" b="837">s</charParams></formatting></line></par>
</text></cell></row>
<row>
<cell width="463" height="42">
<text>
<par lineSpacing="920"></par>
</text></cell>
<cell width="107" height="42">
<text>
<par align="Center" lineSpacing="1008">
<line baseline="861" l="700" t="847" r="750" b="860"><formatting lang="EnglishUnitedStates">
<charParams l="700" t="848" r="707" b="860">t</charParams>
<charParams l="708" t="850" r="718" b="860">o</charParams>
<charParams l="719" t="850" r="724" b="860"> </charParams>
<charParams l="725" t="850" r="734" b="859">a</charParams>
<charParams l="737" t="847" r="740" b="859">i</charParams>
<charParams l="743" t="850" r="750" b="859">r</charParams></formatting></line>
<line baseline="881" l="689" t="868" r="762" b="884"><formatting lang="EnglishUnitedStates">
<charParams l="689" t="868" r="698" b="880">k</charParams>
<charParams l="699" t="871" r="709" b="883">g</charParams>
<charParams l="712" t="868" r="720" b="883">/</charParams>
<charParams l="722" t="871" r="732" b="883">y</charParams>
<charParams l="733" t="871" r="743" b="880">e</charParams>
<charParams l="744" t="871" r="753" b="880">a</charParams>
<charParams l="756" t="871" r="762" b="881">r</charParams></formatting></line></par>
</text></cell>
<cell width="113" height="42">
<text>
<par align="Center" lineSpacing="1008">
<line baseline="859" l="796" t="848" r="874" b="860"><formatting lang="EnglishUnitedStates">
<charParams l="796" t="848" r="803" b="860">t</charParams>
<charParams l="804" t="850" r="813" b="860">o</charParams>
<charParams l="814" t="850" r="820" b="860"> </charParams>
<charParams l="821" t="850" r="835" b="859">w</charParams>
<charParams l="837" t="850" r="846" b="859">a</charParams>
<charParams l="848" t="848" r="854" b="859">t</charParams>
<charParams l="856" t="850" r="865" b="859">e</charParams>
<charParams l="867" t="850" r="874" b="859">r</charParams></formatting></line>
<line baseline="880" l="798" t="868" r="872" b="883"><formatting lang="EnglishUnitedStates">
<charParams l="798" t="868" r="808" b="881">k</charParams>
<charParams l="809" t="871" r="818" b="883">g</charParams>
<charParams l="821" t="868" r="829" b="883">/</charParams>
<charParams l="832" t="871" r="841" b="883">y</charParams>
<charParams l="843" t="871" r="852" b="880">e</charParams>
<charParams l="854" t="871" r="863" b="880">a</charParams>
<charParams l="866" t="871" r="872" b="880">r</charParams></formatting></line></par>
</text></cell>
<cell width="140" height="42">
<text>
<par align="Center" lineSpacing="1008">
<line baseline="858" l="929" t="847" r="992" b="860"><formatting lang="EnglishUnitedStates">
<charParams l="929" t="848" r="936" b="860">t</charParams>
<charParams l="937" t="850" r="946" b="860">o</charParams>
<charParams l="947" t="847" r="953" b="860"> </charParams>
<charParams l="954" t="847" r="957" b="859">l</charParams>
<charParams l="960" t="850" r="968" b="859">a</charParams>
<charParams l="971" t="850" r="980" b="859">n</charParams>
<charParams l="983" t="847" r="992" b="859">d</charParams></formatting></line>
<line baseline="879" l="925" t="868" r="998" b="884"><formatting lang="EnglishUnitedStates">
<charParams l="925" t="868" r="934" b="880">k</charParams>
<charParams l="935" t="871" r="944" b="883">g</charParams>
<charParams l="947" t="868" r="955" b="883">/</charParams>
<charParams l="958" t="871" r="967" b="883">y</charParams>
<charParams l="969" t="871" r="978" b="880">e</charParams>
<charParams l="980" t="871" r="989" b="880">a</charParams>
<charParams l="992" t="871" r="998" b="881">r</charParams></formatting></line></par>
</text></cell></row>
<row>
<cell width="463" height="21">
<text>
<par lineSpacing="920">
<line baseline="904" l="221" t="889" r="304" b="902"><formatting lang="EnglishUnitedStates">
<charParams l="221" t="889" r="232" b="901">A</charParams>
<charParams l="234" t="892" r="242" b="901">s</charParams>
<charParams l="245" t="889" r="254" b="901">b</charParams>
<charParams l="255" t="892" r="265" b="901">e</charParams>
<charParams l="267" t="892" r="275" b="901">s</charParams>
<charParams l="276" t="889" r="283" b="901">t</charParams>
<charParams l="284" t="893" r="294" b="902">o</charParams>
<charParams l="296" t="893" r="304" b="902">s</charParams></formatting></line></par>
</text></cell>
<cell width="107" height="21">
<text>
<par align="Center" lineSpacing="980">
<line baseline="903" l="722" t="889" r="729" b="902"><formatting lang="EnglishUnitedStates">
<charParams l="722" t="889" r="729" b="902">1</charParams></formatting></line></par>
</text></cell>
<cell width="113" height="21">
<text>
<par align="Center" lineSpacing="980">
<line baseline="902" l="831" t="889" r="838" b="902"><formatting lang="EnglishUnitedStates">
<charParams l="831" t="889" r="838" b="902">1</charParams></formatting></line></par>
</text></cell>
<cell width="140" height="21">
<text>
<par align="Center" lineSpacing="980">
<line baseline="901" l="958" t="889" r="965" b="902"><formatting lang="EnglishUnitedStates">
<charParams l="958" t="889" r="965" b="902">1</charParams></formatting></line></par>
</text></cell></row>
<row>
<cell width="463" height="21">
<text>
<par lineSpacing="920">
<line baseline="925" l="221" t="908" r="424" b="927"><formatting lang="EnglishUnitedStates">
<charParams l="221" t="910" r="231" b="922">C</charParams>
<charParams l="234" t="910" r="243" b="922">h</charParams>
<charParams l="246" t="910" r="248" b="922">l</charParams>
<charParams l="251" t="913" r="261" b="922">o</charParams>
<charParams l="263" t="913" r="269" b="922">r</charParams>
<charParams l="271" t="909" r="274" b="922">i</charParams>
<charParams l="276" t="910" r="285" b="922">d</charParams>
<charParams l="288" t="913" r="297" b="922">e</charParams>
<charParams l="299" t="914" r="307" b="923">s</charParams>
<charParams l="308" t="910" r="314" b="927"> </charParams>
<charParams l="315" t="910" r="320" b="927">(</charParams>
<charParams l="323" t="914" r="332" b="923">a</charParams>
<charParams l="335" t="913" r="343" b="923">s</charParams>
<charParams l="344" t="911" r="349" b="923"> </charParams>
<charParams l="350" t="911" r="356" b="923">t</charParams>
<charParams l="358" t="913" r="367" b="923">o</charParams>
<charParams l="369" t="911" r="375" b="922">t</charParams>
<charParams l="377" t="913" r="385" b="922">a</charParams>
<charParams l="389" t="910" r="391" b="922">l</charParams>
<charParams l="392" t="910" r="399" b="922"> </charParams>
<charParams l="400" t="910" r="410" b="922">C</charParams>
<charParams l="412" t="909" r="415" b="922">l</charParams>
<charParams l="419" t="909" r="424" b="926">)</charParams></formatting></line></par>
</text></cell>
<cell width="107" height="21">
<text>
<par align="Center" lineSpacing="920">
<line baseline="921" l="722" t="916" r="728" b="918"><formatting lang="EnglishUnitedStates">
<charParams l="722" t="916" r="728" b="918">-</charParams></formatting></line></par>
</text></cell>
<cell width="113" height="21">
<text>
<par align="Center" lineSpacing="980">
<line baseline="922" l="800" t="910" r="869" b="924"><formatting lang="EnglishUnitedStates">
<charParams l="800" t="910" r="809" b="923">2</charParams>
<charParams l="810" t="910" r="816" b="923"> </charParams>
<charParams l="817" t="913" r="831" b="922">m</charParams>
<charParams l="833" t="910" r="835" b="922">i</charParams>
<charParams l="837" t="910" r="839" b="922">l</charParams>
<charParams l="842" t="910" r="844" b="922">l</charParams>
<charParams l="847" t="910" r="849" b="922">i</charParams>
<charParams l="851" t="913" r="859" b="923">o</charParams>
<charParams l="861" t="912" r="869" b="923">n</charParams></formatting></line></par>
</text></cell>
<cell width="140" height="21">
<text>
<par startIndent="1500" lineSpacing="980">
<line baseline="921" l="926" t="909" r="995" b="924"><formatting lang="EnglishUnitedStates">
<charParams l="926" t="910" r="935" b="923">2</charParams>
<charParams l="936" t="910" r="942" b="923"> </charParams>
<charParams l="943" t="913" r="957" b="922">m</charParams>
<charParams l="959" t="910" r="961" b="922">i</charParams>
<charParams l="963" t="910" r="965" b="922">l</charParams>
<charParams l="968" t="909" r="970" b="922">l</charParams>
<charParams l="973" t="910" r="975" b="922">i</charParams>
<charParams l="977" t="912" r="985" b="923">o</charParams>
<charParams l="987" t="913" r="995" b="923">n</charParams></formatting></line></par>
</text></cell></row>
<row>
<cell width="463" height="22">
<text>
<par lineSpacing="920">
<line baseline="946" l="221" t="929" r="429" b="949"><formatting lang="EnglishUnitedStates">
<charParams l="221" t="931" r="232" b="943">C</charParams>
<charParams l="233" t="934" r="242" b="947">y</charParams>
<charParams l="244" t="934" r="253" b="943">a</charParams>
<charParams l="256" t="934" r="265" b="943">n</charParams>
<charParams l="268" t="931" r="271" b="943">i</charParams>
<charParams l="273" t="931" r="282" b="943">d</charParams>
<charParams l="284" t="934" r="294" b="943">e</charParams>
<charParams l="295" t="934" r="304" b="943">s</charParams>
<charParams l="305" t="930" r="311" b="947"> </charParams>
<charParams l="312" t="931" r="317" b="947">(</charParams>
<charParams l="320" t="935" r="329" b="944">a</charParams>
<charParams l="331" t="934" r="340" b="944">s</charParams>
<charParams l="341" t="932" r="345" b="944"> </charParams>
<charParams l="346" t="932" r="353" b="944">t</charParams>
<charParams l="354" t="934" r="364" b="944">o</charParams>
<charParams l="365" t="932" r="372" b="944">t</charParams>
<charParams l="373" t="934" r="382" b="944">a</charParams>
<charParams l="385" t="931" r="388" b="943">l</charParams>
<charParams l="389" t="931" r="395" b="943"> </charParams>
<charParams l="396" t="931" r="406" b="943">C</charParams>
<charParams l="409" t="931" r="420" b="943">N</charParams>
<charParams l="423" t="930" r="429" b="947">)</charParams></formatting></line></par>
</text></cell>
<cell width="107" height="22">
<text>
<par align="Center" lineSpacing="920">
<line baseline="943" l="722" t="937" r="728" b="939"><formatting lang="EnglishUnitedStates">
<charParams l="722" t="937" r="728" b="939">-</charParams></formatting></line></par>
</text></cell>
<cell width="113" height="22">
<text>
<par align="Center" lineSpacing="980">
<line baseline="944" l="826" t="931" r="845" b="944"><formatting lang="EnglishUnitedStates">
<charParams l="826" t="931" r="834" b="944">5</charParams>
<charParams l="836" t="931" r="845" b="944">0</charParams></formatting></line></par>
</text></cell>
<cell width="140" height="22">
<text>
<par align="Center" lineSpacing="980">
<line baseline="943" l="952" t="931" r="971" b="944"><formatting lang="EnglishUnitedStates">
<charParams l="952" t="931" r="960" b="944">5</charParams>
<charParams l="962" t="931" r="971" b="944">0</charParams></formatting></line></par>
</text></cell></row>
<row>
<cell width="463" height="21">
<text>
<par lineSpacing="920">
<line baseline="968" l="222" t="952" r="415" b="969"><formatting lang="EnglishUnitedStates">
<charParams l="222" t="953" r="230" b="965">F</charParams>
<charParams l="232" t="953" r="235" b="965">l</charParams>
<charParams l="238" t="956" r="247" b="965">u</charParams>
<charParams l="249" t="956" r="259" b="965">o</charParams>
<charParams l="262" t="956" r="268" b="965">r</charParams>
<charParams l="270" t="953" r="273" b="965">i</charParams>
<charParams l="275" t="953" r="284" b="965">d</charParams>
<charParams l="287" t="956" r="296" b="965">e</charParams>
<charParams l="298" t="956" r="306" b="965">s</charParams>
<charParams l="307" t="952" r="313" b="968"> </charParams>
<charParams l="314" t="953" r="319" b="969">(</charParams>
<charParams l="322" t="957" r="331" b="966">a</charParams>
<charParams l="333" t="957" r="342" b="966">s</charParams>
<charParams l="343" t="954" r="347" b="966"> </charParams>
<charParams l="348" t="954" r="355" b="966">t</charParams>
<charParams l="357" t="956" r="366" b="966">o</charParams>
<charParams l="367" t="954" r="374" b="966">t</charParams>
<charParams l="376" t="956" r="384" b="966">a</charParams>
<charParams l="387" t="953" r="390" b="965">l</charParams>
<charParams l="391" t="953" r="398" b="965"> </charParams>
<charParams l="399" t="953" r="407" b="965">F</charParams>
<charParams l="410" t="953" r="415" b="969">)</charParams></formatting></line></par>
</text></cell>
<cell width="107" height="21">
<text>
<par align="Center" lineSpacing="920">
<line baseline="964" l="722" t="959" r="728" b="961"><formatting lang="EnglishUnitedStates">
<charParams l="722" t="959" r="728" b="961">-</charParams></formatting></line></par>
</text></cell>
<cell width="113" height="21">
<text>
<par align="Center" lineSpacing="980">
<line baseline="965" l="812" t="953" r="858" b="967"><formatting lang="EnglishUnitedStates">
<charParams l="812" t="953" r="820" b="966">2</charParams>
<charParams l="821" t="953" r="827" b="966"> </charParams>
<charParams l="828" t="953" r="837" b="966">0</charParams>
<charParams l="839" t="953" r="847" b="966">0</charParams>
<charParams l="849" t="953" r="858" b="966">0</charParams></formatting></line></par>
</text></cell>
<cell width="140" height="21">
<text>
<par align="Center" lineSpacing="980">
<line baseline="964" l="938" t="952" r="984" b="967"><formatting lang="EnglishUnitedStates">
<charParams l="938" t="953" r="946" b="965">2</charParams>
<charParams l="947" t="953" r="953" b="966"> </charParams>
<charParams l="954" t="953" r="963" b="966">0</charParams>
<charParams l="965" t="952" r="974" b="966">0</charParams>
<charParams l="975" t="953" r="984" b="966">0</charParams></formatting></line></par>
</text></cell></row>
<row>
<cell width="463" height="21">
<text>
<par lineSpacing="920">
<line baseline="988" l="222" t="972" r="465" b="991"><formatting lang="EnglishUnitedStates">
<charParams l="222" t="975" r="232" b="986">P</charParams>
<charParams l="233" t="977" r="242" b="986">a</charParams>
<charParams l="245" t="977" r="252" b="986">r</charParams>
<charParams l="252" t="975" r="259" b="986">t</charParams>
<charParams l="261" t="974" r="264" b="986">i</charParams>
<charParams l="266" t="977" r="274" b="986">c</charParams>
<charParams l="276" t="977" r="285" b="986">u</charParams>
<charParams l="288" t="974" r="291" b="986">l</charParams>
<charParams l="293" t="977" r="302" b="986">a</charParams>
<charParams l="304" t="974" r="311" b="986">t</charParams>
<charParams l="312" t="977" r="322" b="987">e</charParams>
<charParams l="323" t="978" r="328" b="987"> </charParams>
<charParams l="329" t="978" r="344" b="987">m</charParams>
<charParams l="347" t="977" r="356" b="987">a</charParams>
<charParams l="357" t="975" r="364" b="987">t</charParams>
<charParams l="365" t="975" r="372" b="987">t</charParams>
<charParams l="373" t="977" r="382" b="987">e</charParams>
<charParams l="384" t="977" r="391" b="986">r</charParams>
<charParams l="392" t="974" r="398" b="990"> </charParams>
<charParams l="399" t="974" r="404" b="990">(</charParams>
<charParams l="408" t="974" r="417" b="986">P</charParams>
<charParams l="420" t="974" r="432" b="987">M</charParams>
<charParams l="436" t="975" r="444" b="987">1</charParams>
<charParams l="447" t="975" r="457" b="987">0</charParams>
<charParams l="460" t="974" r="465" b="990">)</charParams></formatting></line></par>
</text></cell>
<cell width="107" height="21">
<text>
<par align="Center" lineSpacing="980">
<line baseline="988" l="697" t="973" r="754" b="988"><formatting lang="EnglishUnitedStates">
<charParams l="697" t="974" r="705" b="987">5</charParams>
<charParams l="707" t="974" r="716" b="987">0</charParams>
<charParams l="717" t="974" r="723" b="987"> </charParams>
<charParams l="724" t="974" r="732" b="987">0</charParams>
<charParams l="734" t="974" r="743" b="987">0</charParams>
<charParams l="745" t="973" r="754" b="987">0</charParams></formatting></line></par>
</text></cell>
<cell width="113" height="21">
<text>
<par align="Center" lineSpacing="920">
<line baseline="984" l="832" t="980" r="838" b="982"><formatting lang="EnglishUnitedStates">
<charParams l="832" t="980" r="838" b="982">-</charParams></formatting></line></par>
</text></cell>
<cell width="140" height="21">
<text>
<par leftIndent="1500" lineSpacing="920"></par>
</text></cell></row>
<row>
<cell width="463" height="21">
<text>
<par lineSpacing="920">
<line baseline="1010" l="221" t="995" r="354" b="1011"><formatting lang="EnglishUnitedStates">
<charParams l="221" t="995" r="231" b="1007">T</charParams>
<charParams l="233" t="998" r="242" b="1008">o</charParams>
<charParams l="243" t="996" r="250" b="1008">t</charParams>
<charParams l="252" t="998" r="260" b="1007">a</charParams>
<charParams l="263" t="995" r="266" b="1007">l</charParams>
<charParams l="267" t="995" r="274" b="1007"> </charParams>
<charParams l="275" t="995" r="286" b="1007">N</charParams>
<charParams l="289" t="995" r="292" b="1007">i</charParams>
<charParams l="293" t="996" r="300" b="1007">t</charParams>
<charParams l="302" t="998" r="309" b="1007">r</charParams>
<charParams l="310" t="998" r="319" b="1007">o</charParams>
<charParams l="321" t="998" r="330" b="1011">g</charParams>
<charParams l="333" t="999" r="342" b="1008">e</charParams>
<charParams l="344" t="999" r="354" b="1008">n</charParams></formatting></line></par>
</text></cell>
<cell width="107" height="21">
<text>
<par align="Center" lineSpacing="920">
<line baseline="1006" l="722" t="1001" r="728" b="1003"><formatting lang="EnglishUnitedStates">
<charParams l="722" t="1001" r="728" b="1003">-</charParams></formatting></line></par>
</text></cell>
<cell width="113" height="21">
<text>
<par align="Center" lineSpacing="980">
<line baseline="1008" l="807" t="994" r="863" b="1009"><formatting lang="EnglishUnitedStates">
<charParams l="807" t="995" r="815" b="1008">5</charParams>
<charParams l="817" t="995" r="826" b="1008">0</charParams>
<charParams l="827" t="995" r="832" b="1008"> </charParams>
<charParams l="833" t="995" r="842" b="1008">0</charParams>
<charParams l="844" t="995" r="853" b="1008">0</charParams>
<charParams l="855" t="995" r="863" b="1008">0</charParams></formatting></line></par>
</text></cell>
<cell width="140" height="21">
<text>
<par align="Center" lineSpacing="980">
<line baseline="1007" l="933" t="994" r="989" b="1009"><formatting lang="EnglishUnitedStates">
<charParams l="933" t="995" r="941" b="1008">5</charParams>
<charParams l="943" t="995" r="952" b="1008">0</charParams>
<charParams l="953" t="994" r="958" b="1009"> </charParams>
<charParams l="959" t="995" r="968" b="1008">0</charParams>
<charParams l="970" t="995" r="979" b="1008">0</charParams>
<charParams l="981" t="995" r="989" b="1008">0</charParams></formatting></line></par>
</text></cell></row>
<row>
<cell width="463" height="25">
<text>
<par lineSpacing="920">
<line baseline="1032" l="221" t="1016" r="383" b="1033"><formatting lang="EnglishUnitedStates">
<charParams l="221" t="1018" r="231" b="1029">T</charParams>
<charParams l="232" t="1020" r="242" b="1030">o</charParams>
<charParams l="243" t="1018" r="250" b="1030">t</charParams>
<charParams l="251" t="1020" r="260" b="1030">a</charParams>
<charParams l="263" t="1017" r="266" b="1029">l</charParams>
<charParams l="267" t="1017" r="274" b="1029"> </charParams>
<charParams l="275" t="1018" r="285" b="1029">P</charParams>
<charParams l="287" t="1017" r="296" b="1029">h</charParams>
<charParams l="298" t="1020" r="308" b="1029">o</charParams>
<charParams l="310" t="1020" r="318" b="1029">s</charParams>
<charParams l="320" t="1020" r="329" b="1033">p</charParams>
<charParams l="332" t="1017" r="341" b="1030">h</charParams>
<charParams l="343" t="1021" r="353" b="1030">o</charParams>
<charParams l="355" t="1021" r="361" b="1030">r</charParams>
<charParams l="363" t="1021" r="372" b="1030">u</charParams>
<charParams l="374" t="1020" r="383" b="1030">s</charParams></formatting></line></par>
</text></cell>
<cell width="107" height="25">
<text>
<par align="Center" lineSpacing="920">
<line baseline="1030" l="722" t="1023" r="728" b="1025"><formatting lang="EnglishUnitedStates">
<charParams l="722" t="1023" r="728" b="1025">-</charParams></formatting></line></par>
</text></cell>
<cell width="113" height="25">
<text>
<par align="Center" lineSpacing="980">
<line baseline="1029" l="812" t="1016" r="858" b="1031"><formatting lang="EnglishUnitedStates">
<charParams l="812" t="1017" r="820" b="1030">5</charParams>
<charParams l="821" t="1017" r="827" b="1030"> </charParams>
<charParams l="828" t="1017" r="837" b="1030">0</charParams>
<charParams l="839" t="1017" r="847" b="1030">0</charParams>
<charParams l="849" t="1016" r="858" b="1030">0</charParams></formatting></line></par>
</text></cell>
<cell width="140" height="25">
<text>
<par align="Center" lineSpacing="980">
<line baseline="1029" l="938" t="1016" r="984" b="1031"><formatting lang="EnglishUnitedStates">
<charParams l="938" t="1017" r="946" b="1030">5</charParams>
<charParams l="947" t="1016" r="953" b="1031"> </charParams>
<charParams l="954" t="1017" r="963" b="1030">0</charParams>
<charParams l="965" t="1017" r="974" b="1030">0</charParams>
<charParams l="975" t="1017" r="984" b="1030">0</charParams></formatting></line></par>
</text></cell></row>
</block>
<block blockType="SeparatorsBox" blockName="" l="203" t="195" r="1038" b="731"><region><rect l="424" t="195" r="1037" b="196"/><rect l="203" t="196" r="1038" b="198"/><rect l="203" t="198" r="1038" b="199"/><rect l="203" t="199" r="1038" b="723"/><rect l="203" t="723" r="1038" b="724"/><rect l="203" t="724" r="1038" b="725"/><rect l="203" t="725" r="1038" b="726"/><rect l="203" t="726" r="1038" b="727"/><rect l="203" t="727" r="1038" b="728"/><rect l="233" t="728" r="1038" b="729"/><rect l="513" t="729" r="1037" b="730"/><rect l="860" t="730" r="1037" b="731"/></region>
<separatorsBox>
<separator type="Black" thickness="2"><start x="203" y="197"/><end x="1037" y="196"/>
</separator>
<separator type="Black" thickness="3"><start x="203" y="725"/><end x="1037" y="728"/>
</separator>
<separator type="Black" thickness="2"><start x="204" y="196"/><end x="204" y="728"/>
</separator>
<separator type="Black" thickness="2"><start x="1037" y="196"/><end x="1037" y="728"/>
</separator>
</separatorsBox>
</block>
<block blockType="Separator" blockName="" l="146" t="174" r="1096" b="177"><region><rect l="424" t="174" r="1032" b="175"/><rect l="146" t="175" r="1096" b="176"/><rect l="146" t="176" r="1096" b="177"/></region>
<separator type="Black" thickness="2"><start x="146" y="176"/><end x="1096" y="174"/>
</separator>
</block>
<block blockType="Separator" blockName="" l="203" t="222" r="1038" b="225"><region><rect l="416" t="222" r="1038" b="223"/><rect l="203" t="223" r="1038" b="224"/><rect l="203" t="224" r="992" b="225"/></region>
<separator type="Black" thickness="2"><start x="203" y="224"/><end x="1038" y="223"/>
</separator>
</block>
<block blockType="Separator" blockName="" l="203" t="263" r="1037" b="266"><region><rect l="416" t="263" r="865" b="264"/><rect l="203" t="264" r="1037" b="265"/><rect l="203" t="265" r="1037" b="266"/></region>
<separator type="Black" thickness="2"><start x="203" y="265"/><end x="1037" y="264"/>
</separator>
</block>
<block blockType="Separator" blockName="" l="203" t="285" r="1038" b="288"><region><rect l="416" t="285" r="849" b="286"/><rect l="203" t="286" r="1038" b="287"/><rect l="203" t="287" r="1038" b="288"/></region>
<separator type="Black" thickness="2"><start x="203" y="287"/><end x="1038" y="286"/>
</separator>
</block>
<block blockType="Separator" blockName="" l="203" t="326" r="1038" b="329"><region><rect l="414" t="326" r="785" b="327"/><rect l="203" t="327" r="1038" b="328"/><rect l="203" t="328" r="1038" b="329"/></region>
<separator type="Black" thickness="2"><start x="203" y="328"/><end x="1038" y="327"/>
</separator>
</block>
<block blockType="Separator" blockName="" l="203" t="346" r="1038" b="349"><region><rect l="410" t="346" r="753" b="347"/><rect l="203" t="347" r="1038" b="349"/></region>
<separator type="Black" thickness="2"><start x="203" y="347"/><end x="1038" y="347"/>
</separator>
</block>
<block blockType="Separator" blockName="" l="203" t="369" r="1038" b="372"><region><rect l="408" t="369" r="737" b="370"/><rect l="203" t="370" r="1038" b="371"/><rect l="203" t="371" r="1038" b="372"/></region>
<separator type="Black" thickness="2"><start x="203" y="370"/><end x="1038" y="371"/>
</separator>
</block>
<block blockType="Separator" blockName="" l="203" t="410" r="1038" b="413"><region><rect l="400" t="410" r="721" b="411"/><rect l="203" t="411" r="1038" b="412"/><rect l="203" t="412" r="1038" b="413"/></region>
<separator type="Black" thickness="2"><start x="203" y="411"/><end x="1038" y="412"/>
</separator>
</block>
<block blockType="Separator" blockName="" l="203" t="431" r="1038" b="435"><region><rect l="400" t="431" r="721" b="432"/><rect l="203" t="432" r="1038" b="434"/><rect l="203" t="434" r="1038" b="435"/></region>
<separator type="Black" thickness="3"><start x="203" y="432"/><end x="1038" y="433"/>
</separator>
</block>
<block blockType="Separator" blockName="" l="203" t="453" r="1038" b="456"><region><rect l="391" t="453" r="705" b="454"/><rect l="203" t="454" r="1038" b="455"/><rect l="203" t="455" r="1038" b="456"/></region>
<separator type="Black" thickness="2"><start x="203" y="454"/><end x="1038" y="455"/>
</separator>
</block>
<block blockType="Separator" blockName="" l="203" t="474" r="1038" b="477"><region><rect l="203" t="474" r="705" b="475"/><rect l="203" t="475" r="1014" b="476"/><rect l="221" t="476" r="1038" b="477"/></region>
<separator type="Black" thickness="2"><start x="203" y="475"/><end x="1038" y="476"/>
</separator>
</block>
<block blockType="Separator" blockName="" l="203" t="516" r="1038" b="519"><region><rect l="203" t="516" r="705" b="517"/><rect l="203" t="517" r="972" b="518"/><rect l="513" t="518" r="1038" b="519"/></region>
<separator type="Black" thickness="2"><start x="203" y="517"/><end x="1038" y="518"/>
</separator>
</block>
<block blockType="Separator" blockName="" l="203" t="538" r="1033" b="541"><region><rect l="203" t="538" r="935" b="539"/><rect l="203" t="539" r="1033" b="540"/><rect l="513" t="540" r="1033" b="541"/></region>
<separator type="Black" thickness="2"><start x="203" y="538"/><end x="1033" y="539"/>
</separator>
</block>
<block blockType="Separator" blockName="" l="203" t="558" r="1038" b="562"><region><rect l="203" t="558" r="705" b="559"/><rect l="203" t="559" r="1038" b="560"/><rect l="203" t="560" r="1038" b="561"/><rect l="913" t="561" r="1006" b="562"/></region>
<separator type="Black" thickness="2"><start x="203" y="559"/><end x="1038" y="560"/>
</separator>
</block>
<block blockType="Separator" blockName="" l="203" t="580" r="1038" b="584"><region><rect l="203" t="580" r="1038" b="581"/><rect l="203" t="581" r="1038" b="583"/><rect l="513" t="583" r="992" b="584"/></region>
<separator type="Black" thickness="3"><start x="203" y="580"/><end x="1038" y="582"/>
</separator>
</block>
<block blockType="Separator" blockName="" l="203" t="602" r="1038" b="605"><region><rect l="203" t="602" r="1038" b="603"/><rect l="203" t="603" r="1038" b="604"/><rect l="513" t="604" r="978" b="605"/></region>
<separator type="Black" thickness="2"><start x="203" y="601"/><end x="1038" y="604"/>
</separator>
</block>
<block blockType="Separator" blockName="" l="203" t="643" r="1038" b="646"><region><rect l="203" t="643" r="1038" b="644"/><rect l="203" t="644" r="1038" b="645"/><rect l="513" t="645" r="948" b="646"/></region>
<separator type="Black" thickness="2"><start x="203" y="642"/><end x="1038" y="645"/>
</separator>
</block>
<block blockType="Separator" blockName="" l="203" t="685" r="1038" b="688"><region><rect l="203" t="685" r="1026" b="686"/><rect l="203" t="686" r="1038" b="687"/><rect l="513" t="687" r="1038" b="688"/></region>
<separator type="Black" thickness="2"><start x="203" y="684"/><end x="1038" y="687"/>
</separator>
</block>
<block blockType="Separator" blockName="" l="145" t="793" r="1096" b="800"><region><rect l="759" t="793" r="844" b="794"/><rect l="759" t="794" r="972" b="795"/><rect l="145" t="795" r="1065" b="796"/><rect l="145" t="796" r="1096" b="797"/><rect l="145" t="797" r="1096" b="798"/><rect l="319" t="798" r="1096" b="799"/><rect l="1063" t="799" r="1096" b="800"/></region>
<separator type="Black" thickness="3"><start x="145" y="793"/><end x="1096" y="798"/>
</separator>
</block>
<block blockType="Separator" blockName="" l="209" t="817" r="1032" b="820"><region><rect l="209" t="817" r="1032" b="818"/><rect l="209" t="818" r="1032" b="819"/><rect l="329" t="819" r="1000" b="820"/></region>
<separator type="Black" thickness="2"><start x="209" y="816"/><end x="1032" y="820"/>
</separator>
</block>
<block blockType="Separator" blockName="" l="983" t="843" r="1032" b="845"><region><rect l="983" t="843" r="1032" b="845"/></region>
<separator type="Black" thickness="2"><start x="983" y="843"/><end x="1032" y="844"/>
</separator>
</block>
<block blockType="Separator" blockName="" l="209" t="843" r="983" b="846"><region><rect l="209" t="843" r="955" b="844"/><rect l="209" t="844" r="983" b="845"/><rect l="335" t="845" r="983" b="846"/></region>
<separator type="Black" thickness="2"><start x="209" y="841"/><end x="983" y="845"/>
</separator>
</block>
<block blockType="Separator" blockName="" l="209" t="884" r="1032" b="888"><region><rect l="811" t="884" r="823" b="885"/><rect l="209" t="885" r="1028" b="886"/><rect l="209" t="886" r="1032" b="887"/><rect l="353" t="887" r="1032" b="888"/></region>
<separator type="Black" thickness="2"><start x="209" y="883"/><end x="1032" y="888"/>
</separator>
</block>
<block blockType="Separator" blockName="" l="209" t="904" r="1032" b="911"><region><rect l="736" t="904" r="817" b="905"/><rect l="736" t="905" r="920" b="906"/><rect l="209" t="906" r="1021" b="907"/><rect l="209" t="907" r="1032" b="908"/><rect l="359" t="908" r="1032" b="909"/><rect l="916" t="909" r="1032" b="910"/><rect l="1020" t="910" r="1032" b="911"/></region>
<separator type="Black" thickness="2"><start x="209" y="904"/><end x="1032" y="909"/>
</separator>
</block>
<block blockType="Separator" blockName="" l="964" t="927" r="1032" b="929"><region><rect l="964" t="927" r="1013" b="928"/><rect l="964" t="928" r="1032" b="929"/></region>
<separator type="Black" thickness="2"><start x="964" y="927"/><end x="1032" y="928"/>
</separator>
</block>
<block blockType="Separator" blockName="" l="209" t="927" r="964" b="930"><region><rect l="209" t="927" r="913" b="928"/><rect l="209" t="928" r="964" b="929"/><rect l="361" t="929" r="964" b="930"/></region>
<separator type="Black" thickness="2"><start x="209" y="925"/><end x="964" y="929"/>
</separator>
</block>
<block blockType="Separator" blockName="" l="957" t="949" r="1032" b="951"><region><rect l="957" t="949" r="1007" b="950"/><rect l="957" t="950" r="1032" b="951"/></region>
<separator type="Black" thickness="2"><start x="957" y="949"/><end x="1032" y="950"/>
</separator>
</block>
<block blockType="Separator" blockName="" l="209" t="949" r="957" b="952"><region><rect l="209" t="949" r="902" b="950"/><rect l="209" t="950" r="957" b="951"/><rect l="369" t="951" r="957" b="952"/></region>
<separator type="Black" thickness="2"><start x="209" y="947"/><end x="957" y="951"/>
</separator>
</block>
<block blockType="Separator" blockName="" l="408" t="969" r="1026" b="973"><region><rect l="408" t="969" r="689" b="970"/><rect l="408" t="970" r="1002" b="971"/><rect l="408" t="971" r="1026" b="972"/><rect l="795" t="972" r="1026" b="973"/></region>
<separator type="Black" thickness="2"><start x="408" y="968"/><end x="1026" y="972"/>
</separator>
</block>
<block blockType="Separator" blockName="" l="209" t="970" r="408" b="972"><region><rect l="209" t="970" r="374" b="971"/><rect l="209" t="971" r="408" b="972"/></region>
<separator type="Black" thickness="2"><start x="209" y="970"/><end x="408" y="971"/>
</separator>
</block>
<block blockType="Separator" blockName="" l="209" t="990" r="1018" b="994"><region><rect l="209" t="990" r="223" b="991"/><rect l="209" t="991" r="997" b="992"/><rect l="225" t="992" r="1018" b="993"/><rect l="377" t="993" r="1018" b="994"/></region>
<separator type="Black" thickness="2"><start x="209" y="989"/><end x="1018" y="994"/>
</separator>
</block>
<block blockType="Separator" blockName="" l="209" t="1012" r="1014" b="1016"><region><rect l="209" t="1012" r="245" b="1013"/><rect l="209" t="1013" r="993" b="1014"/><rect l="247" t="1014" r="1014" b="1015"/><rect l="379" t="1015" r="1014" b="1016"/></region>
<separator type="Black" thickness="2"><start x="209" y="1011"/><end x="1014" y="1016"/>
</separator>
</block>
<block blockType="Separator" blockName="" l="209" t="1033" r="1011" b="1037"><region><rect l="209" t="1033" r="257" b="1034"/><rect l="209" t="1034" r="993" b="1035"/><rect l="257" t="1035" r="1011" b="1036"/><rect l="379" t="1036" r="1011" b="1037"/></region>
<separator type="Black" thickness="2"><start x="209" y="1032"/><end x="1011" y="1037"/>
</separator>
</block>
<block blockType="Separator" blockName="" l="209" t="818" r="211" b="1035"><region><rect l="209" t="818" r="211" b="1035"/></region>
<separator type="Black" thickness="2"><start x="210" y="818"/><end x="210" y="1035"/>
</separator>
</block>
<block blockType="Separator" blockName="" l="667" t="196" r="669" b="728"><region><rect l="667" t="196" r="669" b="728"/></region>
<separator type="Black" thickness="2"><start x="668" y="196"/><end x="668" y="728"/>
</separator>
</block>
<block blockType="Separator" blockName="" l="671" t="817" r="673" b="1035"><region><rect l="671" t="817" r="673" b="1035"/></region>
<separator type="Black" thickness="2"><start x="672" y="817"/><end x="672" y="1035"/>
</separator>
</block>
<block blockType="Separator" blockName="" l="778" t="843" r="780" b="1035"><region><rect l="778" t="843" r="780" b="1035"/></region>
<separator type="Black" thickness="2"><start x="779" y="843"/><end x="779" y="1035"/>
</separator>
</block>
<block blockType="Separator" blockName="" l="793" t="223" r="795" b="729"><region><rect l="793" t="223" r="795" b="729"/></region>
<separator type="Black" thickness="2"><start x="794" y="223"/><end x="794" y="729"/>
</separator>
</block>
<block blockType="Separator" blockName="" l="891" t="843" r="893" b="1035"><region><rect l="891" t="843" r="893" b="1035"/></region>
<separator type="Black" thickness="2"><start x="892" y="843"/><end x="892" y="1035"/>
</separator>
</block>
<block blockType="Separator" blockName="" l="905" t="224" r="907" b="728"><region><rect l="905" t="224" r="907" b="728"/></region>
<separator type="Black" thickness="2"><start x="906" y="223"/><end x="906" y="728"/>
</separator>
</block>
<block blockType="Separator" blockName="" l="1030" t="817" r="1032" b="1036"><region><rect l="1030" t="817" r="1032" b="1036"/></region>
<separator type="Black" thickness="2"><start x="1031" y="817"/><end x="1031" y="1036"/>
</separator>
</block>
</page>
</document>